pygematria/__init__.py
pygematria/conv.py
pygematria-0.0.1.dist-info/METADATA
pygematria-0.0.1.dist-info/WHEEL
pygematria-0.0.1.dist-info/licenses/LICENSE
pygematria-0.0.1.dist-info/RECORD
