Metadata-Version: 2.3
Name: pygematria
Version: 0.0.1
Summary: A Python package to facilitate numerological analysis on historical and contemporary texts. 
Project-URL: Homepage, https://github.com/ian-nai/pygematria
Project-URL: Bug Tracker, https://github.com/ian-nai/pygematria/issues
Author-email: Ian Goodale <ianpgoodale@gmail.com>
License:                     GNU GENERAL PUBLIC LICENSE
License-File: LICENSE
Classifier: License :: OSI Approved :: GNU General Public License v3 (GPLv3)
Classifier: Operating System :: OS Independent
Classifier: Programming Language :: Python :: 3
Requires-Python: >=3.7
